ose/__init__.py
ose/constants.py
ose/py.typed
ose/commands/CLICommandContext.py
ose/commands/Command.py
ose/commands/CommandContext.py
ose/commands/ImportExternalCommand.py
ose/commands/ReleaseCommandContext.py
ose/commands/__init__.py
ose/database/Base.py
ose/database/NextId.py
ose/database/Release.py
ose/database/User.py
ose/database/__init__.py
ose/database/migrations/README
ose/database/migrations/alembic.ini
ose/database/migrations/env.py
ose/database/migrations/script.py.mako
ose/database/migrations/versions/244abfc3e657_rename_tables.py
ose/database/migrations/versions/487271aa555d_added_release_artifacts.py
ose/database/migrations/versions/5a12a34c96d8_added_release_repo.py
ose/database/migrations/versions/bbe766649a99_initial_migration.py
ose/index/BucketStorage.py
ose/index/ExtendedStorage.py
ose/index/FileStorage.py
ose/index/__init__.py
ose/index/create_index.py
ose/index/schema.py
ose/model/ColumnMapping.py
ose/model/Diff.py
ose/model/ExcelOntology.py
ose/model/Plugin.py
ose/model/Relation.py
ose/model/ReleaseScript.py
ose/model/RepositoryConfiguration.py
ose/model/Result.py
ose/model/Schema.py
ose/model/Script.py
ose/model/ScriptArgument.py
ose/model/Term.py
ose/model/TermIdentifier.py
ose/model/__init__.py
ose/release/BuildReleaseStep.py
ose/release/GithubPublishReleaseStep.py
ose/release/HumanVerificationReleaseStep.py
ose/release/ImportExternalReleaseStep.py
ose/release/ImportExternalWithGitHubActionsReleaseStep.py
ose/release/MergeReleaseStep.py
ose/release/PreparationReleaseStep.py
ose/release/ReleaseStep.py
ose/release/ValidationReleaseStep.py
ose/release/__init__.py
ose/release/common.py
ose/release/do_release.py
ose/services/ConfigurationService.py
ose/services/FileCache.py
ose/services/LocalConfigurationService.py
ose/services/OntoloyBuildService.py
ose/services/PluginService.py
ose/services/RepositoryConfigurationService.py
ose/services/RobotOntologyBuildService.py
ose/services/__init__.py
ose/services/validation.py
ose/utils/__init__.py
ose_core-0.3.0.dist-info/METADATA
ose_core-0.3.0.dist-info/WHEEL
ose_core-0.3.0.dist-info/top_level.txt
ose_core-0.3.0.dist-info/RECORD
