Metadata-Version: 2.4
Name: ose-core
Version: 0.3.0
Summary: Core library for OntoSpreadEd - Ontology spreadsheet editor
Requires-Python: >=3.12
Requires-Dist: pandas
Requires-Dist: openpyxl
Requires-Dist: jsonschema
Requires-Dist: daff
Requires-Dist: whoosh
Requires-Dist: networkx
Requires-Dist: pydot
Requires-Dist: py-horned-owl
Requires-Dist: ontoutils
Requires-Dist: pyyaml
Requires-Dist: dacite
Requires-Dist: aiohttp
Requires-Dist: async-lru
Requires-Dist: typing-extensions>=4.0
Requires-Dist: urllib3
Requires-Dist: GitHub-Flask
Requires-Dist: Flask-SQLAlchemy==3.1.1
Requires-Dist: Flask-Migrate
Provides-Extra: dev
Requires-Dist: pytest; extra == "dev"
Requires-Dist: ruff; extra == "dev"
